lutils/__init__.py
lutils/utils.py
liforra_utils-0.1.2.dist-info/METADATA
liforra_utils-0.1.2.dist-info/WHEEL
liforra_utils-0.1.2.dist-info/top_level.txt
liforra_utils-0.1.2.dist-info/RECORD
