Metadata-Version: 2.4
Name: liforra-utils
Version: 0.1.2
Summary: Small logging and config helper utilities
Author-email: Liforra <lutils@liforra.de>
License: MIT
Project-URL: Homepage, https://liforra.de
Requires-Python: >=3.8
Provides-Extra: toml
Requires-Dist: toml; extra == "toml"
Provides-Extra: yaml
Requires-Dist: PyYAML; extra == "yaml"
Provides-Extra: colors
Requires-Dist: coloredlogs; extra == "colors"
Provides-Extra: all
Requires-Dist: toml; extra == "all"
Requires-Dist: PyYAML; extra == "all"
Requires-Dist: coloredlogs; extra == "all"
